agio/__init__.py
agio-0.0.1.dist-info/METADATA
agio-0.0.1.dist-info/WHEEL
agio-0.0.1.dist-info/top_level.txt
agio-0.0.1.dist-info/RECORD
